Pointlib/__init__.py
Pointlib/myfunctions.py
Pointlib/pointlib.py
Pointlib-0.1.1.dist-info/METADATA
Pointlib-0.1.1.dist-info/WHEEL
Pointlib-0.1.1.dist-info/top_level.txt
Pointlib-0.1.1.dist-info/RECORD
