Metadata-Version: 2.1
Name: Pointlib
Version: 0.1.1
Summary: Pointlib create for manage point-coordinate in Python code.
Home-page: UNKNOWN
Author: Chayoot Kosiwanich
Author-email: UNKNOWN
License: MIT
Platform: UNKNOWN
